mst_ssh.py
mst_ssh-0.1.2.dist-info/entry_points.txt
mst_ssh-0.1.2.dist-info/WHEEL
mst_ssh-0.1.2.dist-info/METADATA
mst_ssh-0.1.2.dist-info/RECORD
