Metadata-Version: 2.1
Name: mst-ssh
Version: 0.1.2
Summary: A command line utility to setup SSH connection to Missouri S&T's Linux virtual machines
Author: Kevin Lai
Author-email: zlnh4@umsystem.edu
Requires-Python: >=3.8,<4.0
Classifier: Programming Language :: Python :: 3
Classifier: Programming Language :: Python :: 3.8
Classifier: Programming Language :: Python :: 3.9
